{
"apiVersion": "v1",
"kind": "Pod",
"metadata": {"name":"k8s-master"},
"spec":{
  "hostNetwork": true,
  "containers":[
    {
      "name": "controller-manager",
      "image": "gcr.io/google_containers/hyperkube:v1.0.3",
      "command": [
              "/hyperkube",
              "controller-manager",
	      "--service_account_private_key_file=/srv/kubernetes/server.key",
	      "--root_ca_file=/srv/kubernetes/ca.crt",
              "--master=127.0.0.1:8080",
              "--v=2"
        ],
      "volumes": [
              "/srv:/srv"
      ]
 
    },
    {
      "name": "apiserver",
      "image": "gcr.io/google_containers/hyperkube:v1.0.3",
      "command": [
              "/hyperkube",
              "apiserver",
	      "--client-ca-file=/srv/kubernetes/ca.crt",
	      "--tls-cert-file=/srv/kubernetes/server.cert",
	      "--tls-private-key-file=/srv/kubernetes/server.key",
              "--portal-net=10.0.0.1/24",
              "--address=0.0.0.0",
              "--etcd-servers=http://127.0.0.1:4001",
              "--cluster-name=kubernetes",
	      "--admission_control=NamespaceLifecycle,NamespaceExists,LimitRanger,SecurityContextDeny,ServiceAccount,ResourceQuota",
              "--v=2"
        ],
      "volumes": [
              "/srv:/srv"
      ]
    },
    {
      "name": "scheduler",
      "image": "gcr.io/google_containers/hyperkube:v1.0.3",
      "command": [
              "/hyperkube",
              "scheduler",
              "--master=127.0.0.1:8080",
              "--v=2"
        ],
      "volumes": [
              "/srv:/srv"
        ]
    }
  ]
 }
}
